wordcut/LICENSE
wordcut/LICENSE-DICT
wordcut/__init__.py
wordcut/bigthai.txt
wordcut/dict.txt
wordcut/example.py
wordcutpy-0.1.2.dist-info/METADATA
wordcutpy-0.1.2.dist-info/WHEEL
wordcutpy-0.1.2.dist-info/top_level.txt
wordcutpy-0.1.2.dist-info/RECORD
