Metadata-Version: 2.1
Name: wordcutpy
Version: 0.1.2
Summary: Thai word tokenizer written in Python
Home-page: https://github.com/veer66/wordcutpy.git
Author: Vee Satayamas
Author-email: vsatayamas@gmail.com
License: LGPLv3
Platform: UNKNOWN
